maybach_request/__init__.py
maybach_request-0.5.0.dist-info/METADATA
maybach_request-0.5.0.dist-info/WHEEL
maybach_request-0.5.0.dist-info/top_level.txt
maybach_request-0.5.0.dist-info/RECORD
