Metadata-Version: 2.1
Name: maybach-request
Version: 0.5.0
Summary: UNKNOWN
Home-page: https://gitlab.xiguacity.cn/fee/python/maybach_request
Author: cuvee
Author-email: cuizaiyong@xigua.club
License: MIT
Platform: UNKNOWN
